mlaas_sdk/__init__.py
mlaas_sdk/clients/__init__.py
mlaas_sdk/clients/base.py
mlaas_sdk/clients/blockchain.py
mlaas_sdk/clients/sharing.py
mlaas_sdk/clients/training.py
mlaas_sdk/exceptions/MLaaSException.py
mlaas_sdk/exceptions/__init__.py
mlaas_sdk/exceptions/blockchain.py
mlaas_sdk/exceptions/sharing.py
mlaas_sdk/exceptions/training.py
mlaas_sdk/models/DatasetContract.py
mlaas_sdk/models/ModelContract.py
mlaas_sdk/models/ModelContractUnverified.py
mlaas_sdk/models/__init__.py
mlaas_sdk/utils.py
mlaas_sdk-1.0.1.dist-info/METADATA
mlaas_sdk-1.0.1.dist-info/WHEEL
mlaas_sdk-1.0.1.dist-info/RECORD
