Metadata-Version: 2.1
Name: mlaas-sdk
Version: 1.0.1
Summary: IoT-NGIN MLaaS Polyglot Model Sharing Framework Python SDK
License: MIT
Keywords: iot-ngin
Author: ivanvmoreno
Author-email: ivan@ivan.build
Requires-Python: >=3.10,<4.0
Classifier: License :: OSI Approved :: MIT License
Classifier: Programming Language :: Python :: 3
Classifier: Programming Language :: Python :: 3.10
Classifier: Programming Language :: Python :: 3.11
Requires-Dist: pydantic (>=1.10.7,<2.0.0)
Requires-Dist: requests (>=2.28.2,<3.0.0)
